LICENSE
README.md
setup.py
pyavg/__init__.py
pyavg/pyavg.py
pyavg.egg-info/PKG-INFO
pyavg.egg-info/SOURCES.txt
pyavg.egg-info/dependency_links.txt
pyavg.egg-info/requires.txt
pyavg.egg-info/top_level.txt