Metadata-Version: 2.1
Name: pyavg
Version: 0.1.0
Summary: A visual novel framework based on pygame.
Home-page: UNKNOWN
Author: London Class
Author-email: 
License: UNKNOWN
Keywords: python,pygame
Platform: UNKNOWN
Classifier: Development Status :: 1 - Planning
Classifier: Intended Audience :: Developers
Classifier: Programming Language :: Python :: 3
License-File: LICENSE
